{
  "name": "Scheduled Reddit Scraper",
  "nodes": [
    {
      "parameters": {
        "rule": {
          "interval": [
            {
              "field": "cronExpression",
              "expression": "0 2 * * 0"
            }
          ]
        }
      },
      "id": "cron-trigger-reddit",
      "name": "Every Sunday at 2 AM",
      "type": "n8n-nodes-base.scheduleTrigger",
      "typeVersion": 1.2,
      "position": [
        250,
        300
      ]
    },
    {
      "parameters": {
        "command": "cd \"C:/Users/JRiel/prompt-engineering-system/scripts/scrapers\" && python reddit_scraper.py --all --timeframe week --limit 50",
        "options": {}
      },
      "id": "execute-reddit-scraper",
      "name": "Execute Reddit Scraper",
      "type": "n8n-nodes-base.executeCommand",
      "typeVersion": 1,
      "position": [
        470,
        300
      ]
    },
    {
      "parameters": {
        "assignments": {
          "assignments": [
            {
              "id": "extract-stats",
              "name": "scraped_posts",
              "value": "={{ $json.stdout.match(/Total posts scraped: (\\d+)/)?.[1] || '0' }}",
              "type": "string"
            },
            {
              "id": "extract-status",
              "name": "status",
              "value": "={{ $json.exitCode === 0 ? 'success' : 'failed' }}",
              "type": "string"
            },
            {
              "id": "timestamp",
              "name": "timestamp",
              "value": "={{ $now.toISO() }}",
              "type": "string"
            },
            {
              "id": "source",
              "name": "source",
              "value": "reddit",
              "type": "string"
            }
          ]
        },
        "options": {}
      },
      "id": "parse-results",
      "name": "Parse Results",
      "type": "n8n-nodes-base.set",
      "typeVersion": 3.4,
      "position": [
        690,
        300
      ]
    },
    {
      "parameters": {
        "command": "cd \"C:/Users/JRiel/prompt-engineering-system/scripts\" && python embed_output.py",
        "options": {}
      },
      "id": "trigger-ingestion",
      "name": "Trigger Ingestion Pipeline",
      "type": "n8n-nodes-base.executeCommand",
      "typeVersion": 1,
      "position": [
        910,
        300
      ]
    },
    {
      "parameters": {
        "method": "POST",
        "url": "={{ $env.SLACK_WEBHOOK_URL || $env.DISCORD_WEBHOOK_URL }}",
        "authentication": "genericCredentialType",
        "genericAuthType": "httpHeaderAuth",
        "sendBody": true,
        "bodyParameters": {
          "parameters": [
            {
              "name": "text",
              "value": "=Reddit Scraper completed successfully!\n\nPosts scraped: {{ $json.scraped_posts }}\nTime: {{ $json.timestamp }}\nStatus: {{ $json.status }}"
            }
          ]
        },
        "options": {}
      },
      "id": "send-success-notification",
      "name": "Send Success Notification",
      "type": "n8n-nodes-base.httpRequest",
      "typeVersion": 4.2,
      "position": [
        1130,
        200
      ]
    },
    {
      "parameters": {
        "method": "POST",
        "url": "={{ $env.SLACK_WEBHOOK_URL || $env.DISCORD_WEBHOOK_URL }}",
        "authentication": "genericCredentialType",
        "genericAuthType": "httpHeaderAuth",
        "sendBody": true,
        "bodyParameters": {
          "parameters": [
            {
              "name": "text",
              "value": "=Reddit Scraper failed!\n\nError: {{ $json.stderr || $json.error }}\nTime: {{ $now.toISO() }}\nExit code: {{ $json.exitCode }}"
            }
          ]
        },
        "options": {}
      },
      "id": "send-error-notification",
      "name": "Send Error Notification",
      "type": "n8n-nodes-base.httpRequest",
      "typeVersion": 4.2,
      "position": [
        1130,
        400
      ]
    },
    {
      "parameters": {
        "conditions": {
          "options": {
            "caseSensitive": true,
            "leftValue": "",
            "typeValidation": "strict"
          },
          "conditions": [
            {
              "id": "check-exit-code",
              "leftValue": "={{ $json.exitCode }}",
              "rightValue": 0,
              "operator": {
                "type": "number",
                "operation": "equals"
              }
            }
          ],
          "combinator": "and"
        },
        "options": {}
      },
      "id": "check-success",
      "name": "Check Success",
      "type": "n8n-nodes-base.if",
      "typeVersion": 2.1,
      "position": [
        690,
        400
      ]
    }
  ],
  "connections": {
    "Every Sunday at 2 AM": {
      "main": [
        [
          {
            "node": "Execute Reddit Scraper",
            "type": "main",
            "index": 0
          }
        ]
      ]
    },
    "Execute Reddit Scraper": {
      "main": [
        [
          {
            "node": "Parse Results",
            "type": "main",
            "index": 0
          },
          {
            "node": "Check Success",
            "type": "main",
            "index": 0
          }
        ]
      ]
    },
    "Parse Results": {
      "main": [
        [
          {
            "node": "Trigger Ingestion Pipeline",
            "type": "main",
            "index": 0
          }
        ]
      ]
    },
    "Trigger Ingestion Pipeline": {
      "main": [
        [
          {
            "node": "Send Success Notification",
            "type": "main",
            "index": 0
          }
        ]
      ]
    },
    "Check Success": {
      "main": [
        [],
        [
          {
            "node": "Send Error Notification",
            "type": "main",
            "index": 0
          }
        ]
      ]
    }
  },
  "pinData": {},
  "settings": {
    "executionOrder": "v1",
    "saveManualExecutions": true,
    "callerPolicy": "workflowsFromSameOwner",
    "errorWorkflow": "",
    "timezone": "America/New_York",
    "saveDataErrorExecution": "all",
    "saveDataSuccessExecution": "all"
  },
  "staticData": null,
  "tags": [
    {
      "id": "scraper",
      "name": "scraper"
    },
    {
      "id": "reddit",
      "name": "reddit"
    },
    {
      "id": "scheduled",
      "name": "scheduled"
    }
  ],
  "triggerCount": 1,
  "updatedAt": "2025-12-01T00:00:00.000Z",
  "versionId": "1"
}
